{
    "data": "20240905",
    "estrazione": [
        {
            "ruota": "BA",
            "ruotaExtended": "BARI",
            "numeri": [
                36,
                6,
                84,
                33,
                18
            ],
            "numeroOro": 18
        },
        {
            "ruota": "CA",
            "ruotaExtended": "CAGLIARI",
            "numeri": [
                14,
                2,
                13,
                69,
                75
            ],
            "numeroOro": 75
        },
        {
            "ruota": "FI",
            "ruotaExtended": "FIRENZE",
            "numeri": [
                58,
                86,
                8,
                23,
                73
            ],
            "numeroOro": 73
        },
        {
            "ruota": "GE",
            "ruotaExtended": "GENOVA",
            "numeri": [
                77,
                57,
                65,
                6,
                21
            ],
            "numeroOro": 21
        },
        {
            "ruota": "MI",
            "ruotaExtended": "MILANO",
            "numeri": [
                5,
                11,
                74,
                72,
                37
            ],
            "numeroOro": 37
        },
        {
            "ruota": "NA",
            "ruotaExtended": "NAPOLI",
            "numeri": [
                66,
                41,
                65,
                43,
                24
            ],
            "numeroOro": 24
        },
        {
            "ruota": "PA",
            "ruotaExtended": "PALERMO",
            "numeri": [
                67,
                37,
                25,
                3,
                7
            ],
            "numeroOro": 7
        },
        {
            "ruota": "RM",
            "ruotaExtended": "ROMA",
            "numeri": [
                64,
                49,
                87,
                48,
                7
            ],
            "numeroOro": 7
        },
        {
            "ruota": "TO",
            "ruotaExtended": "TORINO",
            "numeri": [
                50,
                18,
                41,
                32,
                55
            ],
            "numeroOro": 55
        },
        {
            "ruota": "VE",
            "ruotaExtended": "VENEZIA",
            "numeri": [
                1,
                16,
                61,
                43,
                34
            ],
            "numeroOro": 34
        },
        {
            "ruota": "RN",
            "ruotaExtended": "NAZIONALE",
            "numeri": [
                16,
                5,
                8,
                34,
                88
            ],
            "numeroOro": 88
        }
    ]
}