{
    "data": "20250703",
    "estrazione": [
        {
            "ruota": "BA",
            "ruotaExtended": "BARI",
            "numeri": [
                33,
                40,
                47,
                65,
                61
            ],
            "numeroOro": 61
        },
        {
            "ruota": "CA",
            "ruotaExtended": "CAGLIARI",
            "numeri": [
                78,
                19,
                74,
                44,
                5
            ],
            "numeroOro": 5
        },
        {
            "ruota": "FI",
            "ruotaExtended": "FIRENZE",
            "numeri": [
                46,
                50,
                38,
                79,
                19
            ],
            "numeroOro": 19
        },
        {
            "ruota": "GE",
            "ruotaExtended": "GENOVA",
            "numeri": [
                72,
                48,
                47,
                66,
                34
            ],
            "numeroOro": 34
        },
        {
            "ruota": "MI",
            "ruotaExtended": "MILANO",
            "numeri": [
                11,
                19,
                37,
                61,
                16
            ],
            "numeroOro": 16
        },
        {
            "ruota": "NA",
            "ruotaExtended": "NAPOLI",
            "numeri": [
                66,
                85,
                20,
                29,
                74
            ],
            "numeroOro": 74
        },
        {
            "ruota": "PA",
            "ruotaExtended": "PALERMO",
            "numeri": [
                46,
                10,
                66,
                76,
                35
            ],
            "numeroOro": 35
        },
        {
            "ruota": "RM",
            "ruotaExtended": "ROMA",
            "numeri": [
                34,
                66,
                75,
                79,
                74
            ],
            "numeroOro": 74
        },
        {
            "ruota": "TO",
            "ruotaExtended": "TORINO",
            "numeri": [
                27,
                33,
                40,
                59,
                10
            ],
            "numeroOro": 10
        },
        {
            "ruota": "VE",
            "ruotaExtended": "VENEZIA",
            "numeri": [
                50,
                26,
                68,
                7,
                30
            ],
            "numeroOro": 30
        },
        {
            "ruota": "RN",
            "ruotaExtended": "NAZIONALE",
            "numeri": [
                4,
                17,
                74,
                46,
                41
            ],
            "numeroOro": 41
        }
    ]
}