{
    "data": "20260625",
    "estrazione": [
        {
            "ruota": "BA",
            "ruotaExtended": "BARI",
            "numeri": [
                18,
                55,
                23,
                57,
                84
            ],
            "numeroOro": 84
        },
        {
            "ruota": "CA",
            "ruotaExtended": "CAGLIARI",
            "numeri": [
                7,
                82,
                45,
                52,
                14
            ],
            "numeroOro": 14
        },
        {
            "ruota": "FI",
            "ruotaExtended": "FIRENZE",
            "numeri": [
                84,
                78,
                39,
                33,
                59
            ],
            "numeroOro": 59
        },
        {
            "ruota": "GE",
            "ruotaExtended": "GENOVA",
            "numeri": [
                42,
                24,
                73,
                17,
                38
            ],
            "numeroOro": 38
        },
        {
            "ruota": "MI",
            "ruotaExtended": "MILANO",
            "numeri": [
                51,
                69,
                38,
                54,
                23
            ],
            "numeroOro": 23
        },
        {
            "ruota": "NA",
            "ruotaExtended": "NAPOLI",
            "numeri": [
                25,
                49,
                75,
                85,
                13
            ],
            "numeroOro": 13
        },
        {
            "ruota": "PA",
            "ruotaExtended": "PALERMO",
            "numeri": [
                5,
                37,
                74,
                28,
                4
            ],
            "numeroOro": 4
        },
        {
            "ruota": "RM",
            "ruotaExtended": "ROMA",
            "numeri": [
                29,
                64,
                63,
                85,
                75
            ],
            "numeroOro": 75
        },
        {
            "ruota": "TO",
            "ruotaExtended": "TORINO",
            "numeri": [
                57,
                23,
                70,
                21,
                68
            ],
            "numeroOro": 68
        },
        {
            "ruota": "VE",
            "ruotaExtended": "VENEZIA",
            "numeri": [
                59,
                11,
                55,
                60,
                14
            ],
            "numeroOro": 14
        },
        {
            "ruota": "RN",
            "ruotaExtended": "NAZIONALE",
            "numeri": [
                14,
                7,
                12,
                72,
                41
            ],
            "numeroOro": 41
        }
    ]
}